pg_bitemporal/__init__.py
pg_bitemporal/django/__init__.py
pg_bitemporal/django/base.py
pg_bitemporal/functions.sql
pg_bitemporal/sqlalchemy/__init__.py
pg_bitemporal/sqlalchemy/base.py
pg_bitemporal/sqlalchemy/writer.py
pg_bitemporal-0.1.0.dist-info/LICENSE.txt
pg_bitemporal-0.1.0.dist-info/WHEEL
pg_bitemporal-0.1.0.dist-info/METADATA
pg_bitemporal-0.1.0.dist-info/RECORD
